{
    "type": "object",
    "properties": {
        "charuco_properties": {
            "type": "object",
            "properties": {
                "charuco_dictionary": {
                    "type": "string",
                    "enum": [
                        "DICT_4X4_50",
                        "DICT_4X4_100",
                        "DICT_4X4_250",
                        "DICT_4X4_1000",
                        "DICT_5X5_50",
                        "DICT_5X5_100",
                        "DICT_5X5_250",
                        "DICT_5X5_1000",
                        "DICT_6X6_50",
                        "DICT_6X6_100",
                        "DICT_6X6_250",
                        "DICT_6X6_1000",
                        "DICT_7X7_50",
                        "DICT_7X7_100",
                        "DICT_7X7_250",
                        "DICT_7X7_1000",
						"DICT_ARUCO_ORIGINAL",
						"DICT_APRILTAG_16h5",
						"DICT_APRILTAG_25h9",
						"DICT_APRILTAG_36h10",
						"DICT_APRILTAG_36h11"
                    ]
                },
                "charuco_squares_x": {
                    "type": "integer",
                    "minimum": 3
                },
                "charuco_squares_y": {
                    "type": "integer",
                    "minimum": 3
                },
                "charuco_square_length": {
                    "type": "number"
                },
                "charuco_marker_length": {
                    "type": "number"
                }
            },
            "required": [
                "charuco_dictionary",
                "charuco_squares_x",
                "charuco_squares_y",
                "charuco_square_length",
                "charuco_marker_length"
            ]
        },
        "marker_properties": {
            "type": "object",
            "properties": {
                "marker_dictionary": {
                    "type": "string",
                    "enum": [
                        "DICT_4X4_50",
                        "DICT_4X4_100",
                        "DICT_4X4_250",
                        "DICT_4X4_1000",
                        "DICT_5X5_50",
                        "DICT_5X5_100",
                        "DICT_5X5_250",
                        "DICT_5X5_1000",
                        "DICT_6X6_50",
                        "DICT_6X6_100",
                        "DICT_6X6_250",
                        "DICT_6X6_1000",
                        "DICT_7X7_50",
                        "DICT_7X7_100",
                        "DICT_7X7_250",
                        "DICT_7X7_1000",
						"DICT_ARUCO_ORIGINAL",
						"DICT_APRILTAG_16h5",
						"DICT_APRILTAG_25h9",
						"DICT_APRILTAG_36h10",
						"DICT_APRILTAG_36h11"
                    ]
                },
                "marker_length": {
                    "type": "number"
                },
                "marker_ids": {
                    "type": "array",
                    "items": {
                        "type": "integer"
                    }
                }
            },
            "required": [
                "marker_dictionary",
                "marker_length"
            ]
        },
		"sync_properties": {
            "type": "object",
            "properties": {
                "marker_dictionary": {
                    "type": "string",
                    "enum": [
                        "DICT_4X4_50",
                        "DICT_4X4_100",
                        "DICT_4X4_250",
                        "DICT_4X4_1000",
                        "DICT_5X5_50",
                        "DICT_5X5_100",
                        "DICT_5X5_250",
                        "DICT_5X5_1000",
                        "DICT_6X6_50",
                        "DICT_6X6_100",
                        "DICT_6X6_250",
                        "DICT_6X6_1000",
                        "DICT_7X7_50",
                        "DICT_7X7_100",
                        "DICT_7X7_250",
                        "DICT_7X7_1000",
						"DICT_ARUCO_ORIGINAL",
						"DICT_APRILTAG_16h5",
						"DICT_APRILTAG_25h9",
						"DICT_APRILTAG_36h10",
						"DICT_APRILTAG_36h11"
                    ]
                },
                "marker_id": {
                    "type": "integer"
                }
            },
            "required": [
                "marker_dictionary",
                "marker_id"
            ]
        },
        "sequence_type": {
            "type": "string",
            "enum": [
                "video",
                "images"
            ]
        },
        "sequence_files": {
            "type": "array",
			"minItems": 1,
            "items": {
                "type": "string"
            }
        },
        "use_threading": {
            "type": "boolean"
        },
        "use_cuda": {
            "type": "boolean"
        },
        "pattern_dimensions": {
            "type": "object",
            "properties": {
                "width": {
                    "type": "integer",
                    "minimum": 2
                },
                "height": {
                    "type": "integer",
                    "minimum": 2
                }
            },
            "required": [
                "width",
                "height"
            ]
        },
        "calibrate_camera": {
            "type": "boolean"
        },
        "calibration_frames": {
            "type": "integer",
            "minimum": 0
        },
        "calibration_range": {
            "type": "object",
            "properties": {
                "begin": {
                    "type": "integer",
                    "minimum": 0
                },
                "end": {
                    "type": "integer",
                    "minimum": 0
                }
            },
            "required": [
                "begin",
                "end"
            ]
        },
        "analysis_range": {
            "type": "object",
            "properties": {
                "begin": {
                    "type": "integer",
                    "minimum": 0
                },
                "end": {
                    "type": "integer",
                    "minimum": 0
                }
            },
            "required": [
                "begin",
                "end"
            ]
        },
        "downsample_scale": {
            "type": "number"
        },
        "downsample_width": {
            "type": "integer",
            "minimum": 1
        },
        "downsample_height": {
            "type": "integer",
            "minimum": 1
        },
        "clear_point_cache": {
            "type": "boolean"
        },
        "use_pose_means": {
            "type": "boolean"
        }
    },
    "required": [
        "sequence_type",
        "sequence_files"
    ],
    "dependencies": {
        "downsample_scale": {
			"allOf": [
				{"not": {"required": ["downsample_width"]}},
				{"not": {"required": ["downsample_height"]}}
			]
		},
        "downsample_width": {
			"allOf": [
				{"not": {"required": ["downsample_scale"]}},
				{"not": {"required": ["downsample_height"]}}
			]
		},
        "downsample_height": {
			"allOf": [
				{"not": {"required": ["downsample_width"]}},
				{"not": {"required": ["downsample_scale"]}}
			]
		}
    },
    "title": "calibration_config",
    "description": "1.0"
}